alchemium/__init__.py
alchemium/base_typing.py
alchemium/errors/__init__.py
alchemium/errors/mappers.py
alchemium/errors/exceptions/__init__.py
alchemium/errors/exceptions/base.py
alchemium/errors/exceptions/builders.py
alchemium/errors/exceptions/integrity.py
alchemium/errors/exceptions/mixins.py
alchemium/errors/exceptions/session.py
alchemium/errors/exceptions/workers.py
alchemium/interfaces/__init__.py
alchemium/interfaces/base.py
alchemium/mixins/__init__.py
alchemium/mixins/base.py
alchemium/mixins/create.py
alchemium/mixins/delete.py
alchemium/mixins/read.py
alchemium/mixins/update.py
alchemium/sqlalchemy_layers/__init__.py
alchemium/sqlalchemy_layers/builders.py
alchemium/sqlalchemy_layers/workers.py
alchemium/uow/__init__.py
alchemium/uow/session.py
alchemium/uow/utils.py
alchemium/utils/__init__.py
alchemium/utils/validators.py
alchemium-0.0.0.dist-info/METADATA
alchemium-0.0.0.dist-info/WHEEL
alchemium-0.0.0.dist-info/top_level.txt
alchemium-0.0.0.dist-info/RECORD
