Metadata-Version: 2.4
Name: alchemium
Version: 0.0.0
Summary: Async SQLAlchemy CRUD Library
Author-email: Artem Tikhanovskii <tikhanovskii@phystech.edu>
License-Expression: MIT
Requires-Python: >=3.8
Requires-Dist: sqlalchemy<3.0,>=2.0
